Metadata-Version: 2.4
Name: dr-agent
Version: 0.1.0
Summary: dr-agent-lib is an agent library for building deep research agents
Author-email: Shannon Shen <zejiang@gmail.com>, Rulin Shao <rulins@cs.washington.edu>
License: MIT
Keywords: agents,ai,research,tools,rag,deep-research
Classifier: Development Status :: 3 - Alpha
Classifier: Intended Audience :: Developers
Classifier: License :: OSI Approved :: MIT License
Classifier: Operating System :: OS Independent
Classifier: Programming Language :: Python :: 3
Classifier: Programming Language :: Python :: 3.10
Classifier: Programming Language :: Python :: 3.11
Classifier: Programming Language :: Python :: 3.12
Classifier: Topic :: Software Development :: Libraries :: Python Modules
Classifier: Topic :: Scientific/Engineering :: Artificial Intelligence
Requires-Python: >=3.10
Requires-Dist: fastmcp==2.11.3
Requires-Dist: python-dotenv
Requires-Dist: requests
Requires-Dist: pydantic
Requires-Dist: tinydb
Requires-Dist: tinydb-serialization
Requires-Dist: tenacity
Requires-Dist: beautifulsoup4
Requires-Dist: pdfplumber
Requires-Dist: lxml
Requires-Dist: aiohttp
Requires-Dist: chardet
Requires-Dist: nltk
Requires-Dist: crawl4ai
Requires-Dist: pyyaml
Requires-Dist: transformers
Requires-Dist: blobfile
Requires-Dist: cohere
Requires-Dist: litellm
Requires-Dist: diskcache
Requires-Dist: typer
Requires-Dist: omegaconf
Provides-Extra: dev
Requires-Dist: pytest; extra == "dev"
Requires-Dist: pytest-asyncio; extra == "dev"
Requires-Dist: build; extra == "dev"
Requires-Dist: twine; extra == "dev"
Provides-Extra: vllm
Requires-Dist: vllm; extra == "vllm"
Provides-Extra: all
Requires-Dist: vllm; extra == "all"
